{"system":{"emitters":[{"billboard_origin":"top_center","billboard_type":"axial_self","category":"beam","color":[0.0,1.0,1.0,1.0],"diffuse":"$CONTENT_DATA/Particles/Textures/Glow/WhiteSquare.tga","direction_type":"shape","duration":0.10,"editorColor":[0.0,1.0,1.0,1.0],"effects":[{"control_point":[[0.0,[0.0,1.0,1.0,1.0]],[1.0,[0.0,0.0,0.0,1.0]]],"guid":1,"name":"Color"},{"control_point":[[0.0,0.822350],[1.0,1.157890]],"guid":2,"max_scale":2.0,"name":"Scale"},{"axis":"y-scale","control_point":[[0.0,2500.0],[1.0,2500.0]],"guid":3,"max_scale":2500.0,"name":"Scale"},{"axis":"x-scale","control_point":[[0.0,0.50],[1.0,0.0]],"guid":4,"max_scale":2.0,"name":"Scale"}],"emission_mode":"burst","emission_rate":55,"glow":true,"glow_exposure":10.0,"glow_strength":10.0,"guid":0,"height":2.0,"keep_local":true,"max_particles":1,"name":"Glow pillar","position":[0.0,0.0,0.50],"rotation":180.0,"rotation_axis":[1.0,0.0,0.0],"scene_blend":"addative","time_to_live":1.0,"velocity":0.0,"width":0.50,"z_offset":0.10}],"min_quality":"low"}}
